setup.py
django_file_archive.egg-info/PKG-INFO
django_file_archive.egg-info/SOURCES.txt
django_file_archive.egg-info/dependency_links.txt
django_file_archive.egg-info/requires.txt
django_file_archive.egg-info/top_level.txt
file_archive/__init__.py
file_archive/admin.py
file_archive/models.py
file_archive/urls.py
file_archive/views.py
file_archive/migrations/0001_initial.py
file_archive/migrations/0002_datetimefield_remove_default.py
file_archive/migrations/__init__.py