Metadata-Version: 1.0
Name: django-file-archive
Version: 0.0.2
Summary: Simple facility for uploading files in the Django admin
Home-page: UNKNOWN
Author: Edmund von der Burg
Author-email: evdb@ecclestoad.co.uk
License: AGPL
Keywords: django upload
Platform: UNKNOWN
